{"regionsAndValues":[{"region":"Москва","value":13322},{"region":"Московская область","value":3167},{"region":"Санкт-Петербург","value":8086},{"region":"Австрия"},{"region":"Алтай","value":432},{"region":"Алтайский край","value":1604},{"region":"Амурская область","value":1},{"region":"Аргентина"},{"region":"Армения"},{"region":"Архангельская область","value":779},{"region":"Башкортостан","value":1870},{"region":"Белгородская область","value":728},{"region":"Бельгия"},{"region":"Болгария"},{"region":"Брянская область"},{"region":"Бурятия","value":380},{"region":"Венгрия"},{"region":"Владимирская область","value":716},{"region":"Волгоградская область","value":1085},{"region":"Вологодская область","value":849},{"region":"Воронежская область","value":2395},{"region":"Германия"},{"region":"Греция"},{"region":"Грузия"},{"region":"Дания"},{"region":"Забайкальский край","value":643},{"region":"Ивановская область","value":906},{"region":"Израиль"},{"region":"Ингушетия","value":2},{"region":"Иркутская область","value":1680},{"region":"Ирландия"},{"region":"Испания"},{"region":"Италия"},{"region":"Казахстан"},{"region":"Калининградская область","value":390},{"region":"Калужская область","value":471},{"region":"Камчатский край"},{"region":"Карелия","value":631},{"region":"Кемеровская область","value":871},{"region":"Кипр"},{"region":"Кировская область","value":1359},{"region":"Коми","value":927},{"region":"Костромская область","value":1001},{"region":"Краснодарский край","value":2137},{"region":"Красноярский край","value":1826},{"region":"Курганская область","value":336},{"region":"Курская область","value":704},{"region":"Кыргызстан"},{"region":"Латвия"},{"region":"Ленинградская область","value":1215},{"region":"Липецкая область","value":628},{"region":"Литва"},{"region":"Марий Эл","value":634},{"region":"Молдова"},{"region":"Мурманская область","value":1},{"region":"Нидерланды"},{"region":"Нижегородская область","value":2528},{"region":"Новгородская область","value":730},{"region":"Новосибирская область","value":3547},{"region":"Норвегия"},{"region":"ОАЭ"},{"region":"Омская область","value":1001},{"region":"Оренбургская область","value":5},{"region":"Орловская область","value":838},{"region":"Пензенская область","value":1297},{"region":"Пермский край","value":2708},{"region":"Польша"},{"region":"Португалия"},{"region":"Приморский край","value":1033},{"region":"Псковская область","value":553},{"region":"Ростовская область","value":2711},{"region":"Рязанская область","value":629},{"region":"США"},{"region":"Самарская область","value":2403},{"region":"Саратовская область","value":1619},{"region":"Саха (Якутия)","value":322},{"region":"Сахалинская область"},{"region":"Свердловская область","value":3005},{"region":"Сербия"},{"region":"Смоленская область","value":2},{"region":"Соединённое Королевство"},{"region":"Ставропольский край","value":5},{"region":"Тайланд"},{"region":"Тамбовская область","value":957},{"region":"Татарстан","value":2465},{"region":"Тверская область","value":506},{"region":"Томская область","value":1257},{"region":"Тульская область","value":1131},{"region":"Турция"},{"region":"Тыва","value":331},{"region":"Тюменская область","value":1467},{"region":"Удмуртия"},{"region":"Узбекистан"},{"region":"Ульяновская область","value":708},{"region":"Франция"},{"region":"Хабаровский край","value":1466},{"region":"Ханты-Мансийский автономный округ","value":4},{"region":"Челябинская область","value":2246},{"region":"Черногория"},{"region":"Чехия"},{"region":"Чувашская Республика","value":1915},{"region":"Швейцария"},{"region":"Шри-Ланка"},{"region":"Ярославская область","value":2129}],"total":93294}
